{
  "collectionName": "components_steps_step_items",
  "info": {
    "displayName": "step-item",
    "description": ""
  },
  "options": {},
  "attributes": {
    "icon": {
      "type": "string",
      "required": true,
      "regex": "^(icofont-|fa-)",
      "unique": false
    },
    "title": {
      "type": "string",
      "required": true,
      "unique": false,
      "maxLength": 20
    },
    "Description": {
      "type": "text",
      "required": true,
      "maxLength": 90
    }
  }
}
